{
  "id": 118012,
  "url": "https://www.stampdata.com/stamp.php?id=118012",
  "funcao": "postage",
  "data_iso": "12/12/1961",
  "issue": "1961",
  "denominacao_raw": "6p",
  "cor": "multicolored",
  "design_type": "",
  "design": "Foudia madagascariensis(1961)",
  "watermark": "mult crown & script CA",
  "dentado_raw": "",
  "tiragem_raw": "",
  "numeros_catalogo": [],
  "ano": 1961,
  "imagem_url": "https://www.stampdata.com/files/thumbs/zf/300px-Colnect-3238-964-Red-Fody-Foudia-madagascariensis.jpg",
  "imagem_url_scraped": true
}