{
  "id": 126104,
  "url": "https://www.stampdata.com/stamp.php?id=126104",
  "funcao": "postage",
  "data_iso": "1940",
  "issue": "1939 no imprint",
  "denominacao_raw": "1p",
  "cor": "gray black",
  "design_type": "",
  "design": "Franco(1939 no imprint)",
  "watermark": "unwmk",
  "dentado_raw": "14",
  "tiragem_raw": "",
  "numeros_catalogo": [],
  "ano": 1940,
  "imagem_url": "https://www.stampdata.com/files/thumbs/zz/300px-Colnect-1326-311-General%C3%ADsimo-Francisco-Franco.jpg",
  "imagem_url_scraped": true
}