{
  "id": 126287,
  "url": "https://www.stampdata.com/stamp.php?id=126287",
  "funcao": "postage",
  "data_iso": "3/24/1959",
  "issue": "Stamp Day 1959",
  "denominacao_raw": "15c",
  "cor": "dark brown & gold",
  "design_type": "Velazquezpaintings",
  "design": "Los Borrachos, by Velazquez",
  "watermark": "unwmk",
  "dentado_raw": "14",
  "tiragem_raw": "",
  "numeros_catalogo": [],
  "ano": 1959,
  "imagem_url": "https://www.stampdata.com/files/thumbs/iu/300px-Colnect-579-682--The-Drinkers---The-Triumph-of-Bacchus--by-Diego-Vel%C3%A1zque.jpg",
  "imagem_url_scraped": true
}