{
  "id": 126517,
  "url": "https://www.stampdata.com/stamp.php?id=126517",
  "funcao": "postage",
  "data_iso": "7/9/1962",
  "issue": "",
  "denominacao_raw": "80c",
  "cor": "multicolored",
  "design_type": "Berruguetesculptures",
  "design": "Apostle Alonso Berruguete",
  "watermark": "unwmk",
  "dentado_raw": "14",
  "tiragem_raw": "",
  "numeros_catalogo": [],
  "ano": 1962,
  "imagem_url": "https://www.stampdata.com/files/thumbs/le/300px-Colnect-597-597--Apostle--Alonso-Berruguete.jpg",
  "imagem_url_scraped": true
}