{
  "id": 126639,
  "url": "https://www.stampdata.com/stamp.php?id=126639",
  "funcao": "postage",
  "data_iso": "4/23/1964",
  "issue": "New York World's Fair 1964",
  "denominacao_raw": "1.50p",
  "cor": "brown & red",
  "design_type": "",
  "design": "Bullfight&Unisphere",
  "watermark": "unwmk",
  "dentado_raw": "14",
  "tiragem_raw": "",
  "numeros_catalogo": [],
  "ano": 1964,
  "imagem_url": "https://www.stampdata.com/files/thumbs/zy/300px-Colnect-617-352-New-York-World-s-Fair.jpg",
  "imagem_url_scraped": true
}