{
  "id": 126693,
  "url": "https://www.stampdata.com/stamp.php?id=126693",
  "funcao": "postage",
  "data_iso": "3/24/1965",
  "issue": "Stamp Day 1965",
  "denominacao_raw": "25c",
  "cor": "dull purple & gold",
  "design_type": "Romero de Torrespaintings",
  "design": "La niña de la jarra",
  "watermark": "unwmk",
  "dentado_raw": "14",
  "tiragem_raw": "",
  "numeros_catalogo": [],
  "ano": 1965,
  "imagem_url": "https://www.stampdata.com/files/thumbs/hz/300px-Colnect-171-126-Girl-with-Jar-Romero-de-Torres.jpg",
  "imagem_url_scraped": true
}