{
  "id": 127075,
  "url": "https://www.stampdata.com/stamp.php?id=127075",
  "funcao": "postage",
  "data_iso": "5/24/1971",
  "issue": "",
  "denominacao_raw": "3p",
  "cor": "multicolored",
  "design_type": "animals(1971 Spain)",
  "design": "Ursus arctos(1971 Spain)",
  "watermark": "unwmk",
  "dentado_raw": "14",
  "tiragem_raw": "",
  "numeros_catalogo": [],
  "ano": 1971,
  "imagem_url": "https://www.stampdata.com/files/thumbs/nz/300px-Colnect-601-844-Brown-Bear-Ursus-arctos.jpg",
  "imagem_url_scraped": true
}