{
  "id": 154068,
  "url": "https://www.stampdata.com/stamp.php?id=154068",
  "funcao": "postage",
  "data_iso": "9/29/1974",
  "issue": "Stamp Day 1974",
  "denominacao_raw": "3p",
  "cor": "gold & multicolored",
  "design_type": "Eduardo Rosalespaintings",
  "design": "Isabel the Catholic Dictating her Will",
  "watermark": "unwmk",
  "dentado_raw": "13",
  "tiragem_raw": "",
  "numeros_catalogo": [],
  "ano": 1974,
  "imagem_url": "https://www.stampdata.com/files/thumbs/is/300px-Colnect-647-508-Testament-of-Isabel-the-Catholic-Rosales.jpg",
  "imagem_url_scraped": true
}