{
  "id": 245529,
  "url": "https://www.stampdata.com/stamp.php?id=245529",
  "funcao": "postage",
  "data_iso": "4/17/1985",
  "issue": "International Year of Youth",
  "denominacao_raw": "17p",
  "cor": "multicolored",
  "design_type": "",
  "design": "",
  "watermark": "unwmk",
  "dentado_raw": "13x13.25",
  "tiragem_raw": "",
  "numeros_catalogo": [],
  "ano": 1985,
  "imagem_url": "https://www.stampdata.com/files/thumbs/na/300px-Colnect-176-342-International-Youth-Year.jpg",
  "imagem_url_scraped": true
}