{
  "id": 245848,
  "url": "https://www.stampdata.com/stamp.php?id=245848",
  "funcao": "postage",
  "data_iso": "11/5/2007",
  "issue": "",
  "denominacao_raw": "0.42€",
  "cor": "multicolored",
  "design_type": "Spanish Painting (2007)",
  "design": "Self portrait Mariano Salvador Maella",
  "watermark": "unwmk",
  "dentado_raw": "",
  "tiragem_raw": "",
  "numeros_catalogo": [
    "WNS ES085.07"
  ],
  "ano": 2007,
  "imagem_url": "https://www.stampdata.com/files/thumbs/z0/300px-ES085.07.jpg",
  "imagem_url_scraped": true
}