{
  "id": 250249,
  "url": "https://www.stampdata.com/stamp.php?id=250249",
  "funcao": "postage",
  "data_iso": "1/17/2008",
  "issue": "Science 2008",
  "denominacao_raw": "0.43€",
  "cor": "multicolored",
  "design_type": "",
  "design": "Meteorology",
  "watermark": "unwmk",
  "dentado_raw": "",
  "tiragem_raw": "",
  "numeros_catalogo": [
    "WNS ES016.08"
  ],
  "ano": 2008,
  "imagem_url": "https://www.stampdata.com/files/thumbs/4z/300px-Colnect-466-384-Meteorology.jpg",
  "imagem_url_scraped": true
}