{
  "id": 363385,
  "url": "https://www.stampdata.com/stamp.php?id=363385",
  "funcao": "postage",
  "data_iso": "7/20/1984",
  "issue": "",
  "denominacao_raw": "6p",
  "cor": "multicolored",
  "design_type": "Composers (1984)",
  "design": "",
  "watermark": "unwmk",
  "dentado_raw": "",
  "tiragem_raw": "",
  "numeros_catalogo": [],
  "ano": 1984,
  "imagem_url": "https://www.stampdata.com/files/thumbs/na/300px-Colnect-1489-474-Pablo-Luna-Carn%C3%A9-1879-%E2%80%93-1942.jpg",
  "imagem_url_scraped": true
}