{
  "id": 363355,
  "url": "https://www.stampdata.com/stamp.php?id=363355",
  "funcao": "postage",
  "data_iso": "11/22/1979",
  "issue": "",
  "denominacao_raw": "25pta",
  "cor": "multicolored",
  "design_type": "Spanish Kings - Habsburg Dynasty",
  "design": "Kings of the House of Austria Felipe III",
  "watermark": "unwmk",
  "dentado_raw": "13.25x13",
  "tiragem_raw": "",
  "numeros_catalogo": [],
  "ano": 1979,
  "imagem_url": "https://www.stampdata.com/files/thumbs/ho/300px-Colnect-174-597-Kings-of-the-House-of-Austria-Felipe-III.jpg",
  "imagem_url_scraped": true
}