{
  "id": 369143,
  "url": "https://www.stampdata.com/stamp.php?id=369143",
  "funcao": "postage",
  "data_iso": "4/21/1986",
  "issue": "60th birthday of Queen Elizabeth II",
  "denominacao_raw": "65p",
  "cor": "multicolored",
  "design_type": "",
  "design": "",
  "watermark": "mult crown & script CA",
  "dentado_raw": "",
  "tiragem_raw": "",
  "numeros_catalogo": [],
  "ano": 1986,
  "imagem_url": "https://www.stampdata.com/files/stash/nt/Colnect-4159-848-At-Crown-Agents-Head-Office-London-1983.jpg",
  "imagem_url_scraped": true
}