{
  "id": 411917,
  "url": "https://www.stampdata.com/stamp.php?id=411917",
  "funcao": "postage",
  "data_iso": "2/29/2012",
  "issue": "500th Anniversary of the Conquest of Navarre",
  "denominacao_raw": "0.85€",
  "cor": "multicolored",
  "design_type": "anniversaries (2012)",
  "design": "",
  "watermark": "unwmk",
  "dentado_raw": "",
  "tiragem_raw": "",
  "numeros_catalogo": [
    "WNS ES025.12"
  ],
  "ano": 2012,
  "imagem_url": "https://www.stampdata.com/files/thumbs/z1/300px-ES025.12.jpg",
  "imagem_url_scraped": true
}