{
  "id": 412090,
  "url": "https://www.stampdata.com/stamp.php?id=412090",
  "funcao": "postage",
  "data_iso": "1/23/2014",
  "issue": "Burgos - Spanish Capital of Gastronomy 2013",
  "denominacao_raw": "0.54€",
  "cor": "multicolored",
  "design_type": "",
  "design": "",
  "watermark": "unwmk",
  "dentado_raw": "",
  "tiragem_raw": "",
  "numeros_catalogo": [
    "WNS ES015.14"
  ],
  "ano": 2014,
  "imagem_url": "https://www.stampdata.com/files/thumbs/z1/300px-ES015.14.jpg",
  "imagem_url_scraped": true
}