{
  "id": 105549,
  "url": "https://www.stampdata.com/stamp.php?id=105549",
  "funcao": "postage",
  "data_iso": "1922",
  "issue": "Ceres",
  "denominacao_raw": "8c",
  "cor": "blue green",
  "design_type": "",
  "design": "Ceres(1912 imprint)",
  "watermark": "unwmk",
  "dentado_raw": "12x11.5",
  "tiragem_raw": "",
  "numeros_catalogo": [],
  "ano": 1922,
  "img_url": "https://www.stampdata.com/files/thumbs/z3/300px-Colnect-166-319-Ceres.jpg",
  "imagem_url": "https://www.stampdata.com/files/thumbs/z3/300px-Colnect-166-319-Ceres.jpg",
  "imagem_url_scraped": true
}