{
  "id": 105803,
  "url": "https://www.stampdata.com/stamp.php?id=105803",
  "funcao": "postage",
  "data_iso": "11/28/1928",
  "issue": "Third Independence",
  "denominacao_raw": "5c",
  "cor": "olive green & black",
  "design_type": "",
  "design": "Battle of Atoleiros",
  "watermark": "unwmk",
  "dentado_raw": "14",
  "tiragem_raw": "",
  "numeros_catalogo": [],
  "ano": 1928,
  "img_url": "https://www.stampdata.com/files/thumbs/az/300px-Colnect-166-966-Nuno-Alvares-Pereira-in-the-Battle-of-Atoleiros-1384.jpg"
}