{
  "id": 158023,
  "url": "https://www.stampdata.com/stamp.php?id=158023",
  "funcao": "postage",
  "data_iso": "7/27/1971",
  "issue": "",
  "denominacao_raw": "10e",
  "cor": "multicolored",
  "design_type": "",
  "design": "President Antonio Salazar",
  "watermark": "unwmk",
  "dentado_raw": "",
  "tiragem_raw": "",
  "numeros_catalogo": [],
  "ano": 1971,
  "img_url": "https://www.stampdata.com/files/thumbs/rz/300px-Colnect-172-351-Salazar-Antonio---perf-13%C2%BD.jpg",
  "imagem_url": "https://www.stampdata.com/files/thumbs/rz/300px-Colnect-172-351-Salazar-Antonio---perf-13%C2%BD.jpg",
  "imagem_url_scraped": true
}