{
  "id": 193553,
  "url": "https://www.stampdata.com/stamp.php?id=193553",
  "funcao": "postage",
  "data_iso": "2/22/2003",
  "issue": "Military College 200th",
  "denominacao_raw": "0.43€",
  "cor": "multicolored",
  "design_type": "military uniforms (2003)",
  "design": "1832 Uniforme de Parada",
  "watermark": "unwmk",
  "dentado_raw": "",
  "tiragem_raw": "",
  "numeros_catalogo": [
    "WNS PT003.03"
  ],
  "ano": 2003,
  "img_url": "",
  "imagem_url": "https://www.stampdata.com/files/stash/z0/PT003.03.jpg",
  "imagem_url_scraped": true
}