{
  "id": 193651,
  "url": "https://www.stampdata.com/stamp.php?id=193651",
  "funcao": "postage",
  "data_iso": "10/9/2003",
  "issue": "History of Glasses in Portugal",
  "denominacao_raw": "0,30€",
  "cor": "multicolored",
  "design_type": "glass objects",
  "design": "",
  "watermark": "unwmk",
  "dentado_raw": "",
  "tiragem_raw": "",
  "numeros_catalogo": [
    "WNS PT101.03"
  ],
  "ano": 2003,
  "img_url": "",
  "imagem_url": "https://www.stampdata.com/files/stash/z0/PT101.03.jpg",
  "imagem_url_scraped": true
}