{
  "id": 255500,
  "url": "https://www.stampdata.com/stamp.php?id=255500",
  "funcao": "postage",
  "data_iso": "11/17/1989",
  "issue": "",
  "denominacao_raw": "100.00e",
  "cor": "multicolored",
  "design_type": "wildflowers (1989)",
  "design": "",
  "watermark": "unwmk",
  "dentado_raw": "",
  "tiragem_raw": "",
  "numeros_catalogo": [],
  "ano": 1989,
  "img_url": "https://www.stampdata.com/files/thumbs/on/300px-Colnect-177-490-Limonium-multiflorum.jpg",
  "imagem_url": "https://www.stampdata.com/files/thumbs/on/300px-Colnect-177-490-Limonium-multiflorum.jpg",
  "imagem_url_scraped": true
}