{
  "id": 335135,
  "url": "https://www.stampdata.com/stamp.php?id=335135",
  "funcao": "postage",
  "data_iso": "6/7/1996",
  "issue": "500th Anniversary of the Death of Joao Vaz Corte-Real",
  "denominacao_raw": "140esc",
  "cor": "multicolored",
  "design_type": "",
  "design": "",
  "watermark": "unwmk",
  "dentado_raw": "",
  "tiragem_raw": "",
  "numeros_catalogo": [],
  "ano": 1996,
  "img_url": "https://www.stampdata.com/files/thumbs/nd/300px-Colnect-179-997-Land-of-Corte-Real.jpg",
  "imagem_url": "https://www.stampdata.com/files/thumbs/nd/300px-Colnect-179-997-Land-of-Corte-Real.jpg",
  "imagem_url_scraped": true
}