{
  "id": 592529,
  "url": "https://www.stampdata.com/stamp.php?id=592529",
  "funcao": "postage",
  "data_iso": "7/9/2016",
  "issue": "Fishes of the Mediterranean",
  "denominacao_raw": "0.80€",
  "cor": "multicolored",
  "design_type": "",
  "design": "Atlantic Mackerel(Scomber scombrus)",
  "watermark": "unwmk",
  "dentado_raw": "13",
  "tiragem_raw": "",
  "numeros_catalogo": [
    "WNS PT051.16"
  ],
  "ano": 2016,
  "img_url": "https://www.stampdata.com/files/thumbs/z1/300px-PT051.16.jpg",
  "imagem_url": "https://www.stampdata.com/files/thumbs/z1/300px-PT051.16.jpg",
  "imagem_url_scraped": true
}