{
  "id": 624748,
  "url": "https://www.stampdata.com/stamp.php?id=624748",
  "funcao": "postage",
  "data_iso": "4/2/2018",
  "issue": "EPAL, 150 Years - The Water that lives within us",
  "denominacao_raw": "1234",
  "cor": "multicolored",
  "design_type": "",
  "design": "",
  "watermark": "unwmk",
  "dentado_raw": "",
  "tiragem_raw": "",
  "numeros_catalogo": [
    "WNS PT027.18"
  ],
  "ano": 2018,
  "img_url": "https://www.stampdata.com/files/thumbs/z1/300px-PT027.18.jpg",
  "imagem_url": "https://www.stampdata.com/files/thumbs/z1/300px-PT027.18.jpg",
  "imagem_url_scraped": true
}