{
  "id": 162935,
  "url": "https://www.stampdata.com/stamp.php?id=162935",
  "funcao": "postage",
  "data_iso": "6/30/2003",
  "issue": "Latina 70th",
  "denominacao_raw": "0,41€",
  "cor": "dull blue",
  "design_type": "",
  "design": "Latina Post Office",
  "watermark": "unwmk",
  "dentado_raw": "14",
  "tiragem_raw": "",
  "numeros_catalogo": [
    "WNS IT028.03"
  ],
  "ano": 2003,
  "imagem_url": "https://www.stampdata.com/files/thumbs/z0/300px-IT028.03.jpg",
  "imagem_url_scraped": true
}