{
  "id": 185323,
  "url": "https://www.stampdata.com/stamp.php?id=185323",
  "funcao": "postage",
  "data_iso": "10/22/2012",
  "issue": "Bicentenary of Birth of Luigi Carlo Farini",
  "denominacao_raw": "0,60€",
  "cor": "multicolored",
  "design_type": "",
  "design": "Luigi Carlo Farini",
  "watermark": "unwmk",
  "dentado_raw": "11",
  "tiragem_raw": "",
  "numeros_catalogo": [
    "WNS IT075.12"
  ],
  "ano": 2012,
  "imagem_url": "https://www.stampdata.com/files/thumbs/z1/300px-IT075.12.jpg",
  "imagem_url_scraped": true
}