{
  "id": 219089,
  "url": "https://www.stampdata.com/stamp.php?id=219089",
  "funcao": "postage",
  "data_iso": "8/21/1963",
  "issue": "Mediterranean Games 1963",
  "denominacao_raw": "15l",
  "cor": "",
  "design_type": "",
  "design": "Bay of Naples & Vesuivius & sailboats",
  "watermark": "stars",
  "dentado_raw": "14",
  "tiragem_raw": "",
  "numeros_catalogo": [],
  "ano": 1963,
  "imagem_url": "https://www.stampdata.com/files/thumbs/gu/300px-Colnect-170-632-Gulf-of-Naples.jpg",
  "imagem_url_scraped": true
}