{
  "id": 244638,
  "url": "https://www.stampdata.com/stamp.php?id=244638",
  "funcao": "postage",
  "data_iso": "11/27/1973",
  "issue": "Christmas 1973",
  "denominacao_raw": "150l",
  "cor": "multicolored",
  "design_type": "",
  "design": "Musician angels",
  "watermark": "stars",
  "dentado_raw": "",
  "tiragem_raw": "",
  "numeros_catalogo": [],
  "ano": 1973,
  "imagem_url": "https://www.stampdata.com/files/thumbs/mu/300px-Colnect-172-820-Musician-angels.jpg",
  "imagem_url_scraped": true
}