{
  "id": 244630,
  "url": "https://www.stampdata.com/stamp.php?id=244630",
  "funcao": "postage",
  "data_iso": "11/5/1973",
  "issue": "",
  "denominacao_raw": "50l",
  "cor": "multicolored",
  "design_type": "Italian artists (1973)",
  "design": "Sandro Filipepi Botticelli",
  "watermark": "stars",
  "dentado_raw": "14x13.5",
  "tiragem_raw": "",
  "numeros_catalogo": [],
  "ano": 1973,
  "imagem_url": "https://www.stampdata.com/files/thumbs/zf/300px-Colnect-172-810-Sandro-Filipepi-Botticelli.jpg",
  "imagem_url_scraped": true
}