{
  "id": 244813,
  "url": "https://www.stampdata.com/stamp.php?id=244813",
  "funcao": "postage",
  "data_iso": "3/16/2007",
  "issue": "",
  "denominacao_raw": "0,60€",
  "cor": "multicolored",
  "design_type": "",
  "design": "Italian Artistic and Cultural Heritage UNESCO Sites - Venezia",
  "watermark": "",
  "dentado_raw": "",
  "tiragem_raw": "",
  "numeros_catalogo": [
    "WNS IT016.07"
  ],
  "ano": 2007,
  "imagem_url": "https://www.stampdata.com/files/thumbs/fz/300px-Colnect-4459-651-Gondola-and-Bridge-of-Rialto-Venice-World-Heritage-1987.jpg",
  "imagem_url_scraped": true
}