{
  "id": 248581,
  "url": "https://www.stampdata.com/stamp.php?id=248581",
  "funcao": "postage",
  "data_iso": "3/24/1990",
  "issue": "World Cup 1990",
  "denominacao_raw": "450(l)",
  "cor": "multicolored",
  "design_type": "",
  "design": "Italy soccer emblem",
  "watermark": "",
  "dentado_raw": "14x13.25",
  "tiragem_raw": "",
  "numeros_catalogo": [],
  "ano": 1990,
  "imagem_url": "https://www.stampdata.com/files/thumbs/oo/300px-Colnect-2828-272-World-Cup-Football-Championship--Italy.jpg",
  "imagem_url_scraped": true
}