{
  "id": 332562,
  "url": "https://www.stampdata.com/stamp.php?id=332562",
  "funcao": "postage",
  "data_iso": "2/12/2009",
  "issue": "Bicentennial of Birth of Charles Darwin",
  "denominacao_raw": "0,65€",
  "cor": "multicolored",
  "design_type": "",
  "design": "Charles Darwin(2009)",
  "watermark": "unwmk",
  "dentado_raw": "13x13.25",
  "tiragem_raw": "",
  "numeros_catalogo": [
    "WNS IT001.09"
  ],
  "ano": 2009,
  "imagem_url": "https://www.stampdata.com/files/thumbs/z0/300px-IT001.09.jpg",
  "imagem_url_scraped": true
}