{
  "id": 410521,
  "url": "https://www.stampdata.com/stamp.php?id=410521",
  "funcao": "postage",
  "data_iso": "6/1/1985",
  "issue": "Tourism 1985",
  "denominacao_raw": "400(l)",
  "cor": "multicolored",
  "design_type": "",
  "design": "Tourist- Castellammare di Stabia",
  "watermark": "stars",
  "dentado_raw": "14",
  "tiragem_raw": "",
  "numeros_catalogo": [],
  "ano": 1985,
  "imagem_url": "https://www.stampdata.com/files/thumbs/ca/300px-Colnect-176-220-Tourist--Castellammare-di-Stabia.jpg",
  "imagem_url_scraped": true
}