{
  "id": 410673,
  "url": "https://www.stampdata.com/stamp.php?id=410673",
  "funcao": "postage",
  "data_iso": "3/20/1996",
  "issue": "",
  "denominacao_raw": "750(l)",
  "cor": "multicolored",
  "design_type": "Italian Wine",
  "design": "",
  "watermark": "unwmk",
  "dentado_raw": "13.25x14",
  "tiragem_raw": "",
  "numeros_catalogo": [],
  "ano": 1996,
  "imagem_url": "https://www.stampdata.com/files/thumbs/ia/300px-Colnect-179-907-Italian-Food---Red-Wine.jpg",
  "imagem_url_scraped": true
}