{
  "id": 410896,
  "url": "https://www.stampdata.com/stamp.php?id=410896",
  "funcao": "postage",
  "data_iso": "10/2/1999",
  "issue": "200th Anniversary of the Death of Giuseppe Parini",
  "denominacao_raw": "800(l)",
  "cor": "multicolored",
  "design_type": "",
  "design": "",
  "watermark": "unwmk",
  "dentado_raw": "",
  "tiragem_raw": "",
  "numeros_catalogo": [],
  "ano": 1999,
  "imagem_url": "https://www.stampdata.com/files/thumbs/pa/300px-Colnect-181-348-Parini-Giuseppe.jpg",
  "imagem_url_scraped": true
}