{
  "id": 410967,
  "url": "https://www.stampdata.com/stamp.php?id=410967",
  "funcao": "postage",
  "data_iso": "8/27/2011",
  "issue": "Winner of the Italian Football Championship Serie A (Milan)",
  "denominacao_raw": "0,60€",
  "cor": "multicolored",
  "design_type": "Italian Sports",
  "design": "",
  "watermark": "unwmk",
  "dentado_raw": "13.5x13",
  "tiragem_raw": "",
  "numeros_catalogo": [
    "WNS IT054.11"
  ],
  "ano": 2011,
  "imagem_url": "https://www.stampdata.com/files/thumbs/z1/300px-IT054.11.jpg",
  "imagem_url_scraped": true
}