{
  "id": 466764,
  "url": "https://www.stampdata.com/stamp.php?id=466764",
  "funcao": "postage",
  "data_iso": "6/19/2015",
  "issue": "150th Anniversary of the Proclamation of Florence as Capital of Italy",
  "denominacao_raw": "0,80€",
  "cor": "multicolored",
  "design_type": "",
  "design": "",
  "watermark": "",
  "dentado_raw": "",
  "tiragem_raw": "",
  "numeros_catalogo": [
    "WNS IT041.15"
  ],
  "ano": 2015,
  "imagem_url": "https://www.stampdata.com/files/thumbs/z1/300px-IT041.15.jpg",
  "imagem_url_scraped": true
}