{
  "id": 586527,
  "url": "https://www.stampdata.com/stamp.php?id=586527",
  "funcao": "postage",
  "data_iso": "5/9/2016",
  "issue": "Europa 2016",
  "denominacao_raw": "1,00€",
  "cor": "multicolored",
  "design_type": "",
  "design": "",
  "watermark": "unwmk",
  "dentado_raw": "11",
  "tiragem_raw": "",
  "numeros_catalogo": [
    "WNS IT035.16"
  ],
  "ano": 2016,
  "imagem_url": "https://www.stampdata.com/files/thumbs/4z/300px-Colnect-3584-734-Think-green.jpg",
  "imagem_url_scraped": true
}