{
  "id": 71756,
  "url": "https://www.stampdata.com/stamp.php?id=71756",
  "funcao": "postage",
  "data_iso": "4/21/1929",
  "issue": "Empire",
  "denominacao_raw": "25c",
  "cor": "deep green",
  "design_type": "",
  "design": "King Vittorio Emanuele III",
  "watermark": "crown (Italy)",
  "dentado_raw": "14",
  "tiragem_raw": "",
  "numeros_catalogo": [],
  "ano": 1929,
  "imagem_url": "https://www.stampdata.com/files/thumbs/tt/300px-Colnect-167-046-Effigy-of-King-Vittorio-Emanuele-III-to-the-left.jpg",
  "imagem_url_scraped": true
}