{
  "id": 71806,
  "url": "https://www.stampdata.com/stamp.php?id=71806",
  "funcao": "postage",
  "data_iso": "3/14/1932",
  "issue": "Dante",
  "denominacao_raw": "10l+2.50l",
  "cor": "green",
  "design_type": "",
  "design": "Dante Alighieri(1932)",
  "watermark": "crown (Italy)",
  "dentado_raw": "14",
  "tiragem_raw": "",
  "numeros_catalogo": [],
  "ano": 1932,
  "imagem_url": "https://www.stampdata.com/files/thumbs/it/300px-Colnect-838-847-Portrait-of-Dante-Alighieri.jpg",
  "imagem_url_scraped": true
}